MANIFEST.in
README.rst
setup.cfg
setup.py
versioneer.py
partysig/__init__.py
partysig/_version.py
partysig/cli.py
partysig/cmd_keygen.py
partysig/cmd_sign.py
partysig/cmd_verify.py
partysig/keystore.py
partysig/util.py
partysig.egg-info/PKG-INFO
partysig.egg-info/SOURCES.txt
partysig.egg-info/dependency_links.txt
partysig.egg-info/entry_points.txt
partysig.egg-info/requires.txt
partysig.egg-info/top_level.txt