Metadata-Version: 1.1
Name: partysig
Version: 0.0.1
Summary: Create and verify distributed multi-party signatures
Home-page: https://github.com/str4d/partysig
Author: Jack Grigg
Author-email: str4d@i2pmail.org
License: MIT
Download-URL: https://github.com/str4d/partysig/tarball/0.0.1
Platform: UNKNOWN
Classifier: Development Status :: 2 - Pre-Alpha
Classifier: Framework :: Twisted
Classifier: Intended Audience :: Developers
Classifier: License :: OSI Approved :: MIT License
Classifier: Operating System :: OS Independent
Classifier: Programming Language :: Python :: 2.7
Classifier: Programming Language :: Python :: 3.5
Classifier: Topic :: Security
